{
  "name": "ipquery.io",
  "url": "https://api.ipquery.io/?format=json",
  "status": "success",
  "elapsed_ms": 48.91,
  "remark": "",
  "supports_ip": false,
  "result": {
    "ip": "52.173.108.23",
    "isp": {
      "asn": "AS8075",
      "org": "Microsoft Corporation",
      "isp": "Microsoft Corporation"
    },
    "location": {
      "country": "United States",
      "country_code": "US",
      "city": "Des Moines",
      "state": "Iowa",
      "zipcode": "50307",
      "latitude": 41.58526899373371,
      "longitude": -93.64457962602545,
      "timezone": "America/Chicago",
      "localtime": "2026-05-01T11:01:35"
    },
    "risk": {
      "is_mobile": false,
      "is_vpn": false,
      "is_tor": false,
      "is_proxy": false,
      "is_datacenter": true,
      "risk_score": 0
    }
  },
  "error": null,
  "test_ip": "8.8.8.8"
}