{
  "name": "wtfismyip.com",
  "url": "https://wtfismyip.com/json",
  "status": "success",
  "elapsed_ms": 1017.24,
  "remark": "",
  "supports_ip": false,
  "result": {
    "YourFuckingIPAddress": "172.172.157.6",
    "YourFuckingLocation": "Washington, VA, United States",
    "YourFuckingHostname": "172.172.157.6",
    "YourFuckingISP": "Microsoft",
    "YourFuckingTorExit": false,
    "YourFuckingCity": "Washington",
    "YourFuckingCountry": "United States",
    "YourFuckingCountryCode": "US"
  },
  "error": null,
  "test_ip": "117.30.120.138"
}